{
  "timestamp": "2025-09-08T21:57:52.474757",
  "symbol": "NAS100",
  "signal_type": "BUY",
  "reliability": 72,
  "entry_price": 1.00049,
  "stop_loss": 0.99749,
  "take_profit": 1.00549,
  "risk_reward": 3.0,
  "timeframe": "H1",
  "technical_scores": {
    "trend": -25,
    "momentum": -11,
    "volatility": 20
  },
  "explanation": "Segnale AI BUY per NAS100. Affidabilità 72%. Segnale robusto supportato da analisi tecnica solida.",
  "volume": 0.01,
  "market_conditions": {
    "volatility": 20,
    "trend_strength": -25,
    "momentum": -11
  }
}